DiscordSR/__init__.py
DiscordSR/guild.py
DiscordSR/mode.py
DiscordSR/other.py
DiscordSR/user.py
DiscordSR/webhook.py
DiscordSR-0.1.5.dist-info/LICENSE
DiscordSR-0.1.5.dist-info/METADATA
DiscordSR-0.1.5.dist-info/WHEEL
DiscordSR-0.1.5.dist-info/top_level.txt
DiscordSR-0.1.5.dist-info/RECORD
