Metadata-Version: 2.1
Name: DiscordSR
Version: 0.1.5
Summary: This library allows http requests to Discord to be simplified.
Author-email: IQminecraft <admin@iqminecraft.net>
Project-URL: Discrd, https://discord.gg/jpKJTpDpN4
Project-URL: issues, https://github.com/IQminecraft/DiscordSR/issues
Project-URL: Author-Homepage, https://iqminecraft.net
Classifier: Programming Language :: Python :: 3
Classifier: License :: OSI Approved :: MIT License
Classifier: Operating System :: OS Independent
Requires-Python: >=3.8
License-File: LICENSE
